volumizer/__init__.py
volumizer/align.py
volumizer/constants.py
volumizer/fib_sphere.py
volumizer/paths.py
volumizer/pdb.py
volumizer/types.py
volumizer/utils.py
volumizer/volumizer.py
volumizer/voxel.py
volumizer-0.1.4.dist-info/LICENSE
volumizer-0.1.4.dist-info/METADATA
volumizer-0.1.4.dist-info/WHEEL
volumizer-0.1.4.dist-info/RECORD
