Metadata-Version: 2.1
Name: volumizer
Version: 0.1.4
Summary: Search the RCSB for occluded volumes like cavities, pockets, and pores.
Author: Aron Broom
Author-email: broomsday@gmail.com
Requires-Python: >=3.10,<4.0
Classifier: Programming Language :: Python :: 3
Classifier: Programming Language :: Python :: 3.10
Classifier: Programming Language :: Python :: 3.11
Requires-Dist: biotite (>=0.37.0,<0.38.0)
Requires-Dist: pyntcloud (>=0.1.5,<0.2.0)
